{
  "formatVersion": 1,
  "database": {
    "version": 2,
    "identityHash": "a6b32dc52c7ca2c525693b6792d3da45",
    "entities": [
      {
        "tableName": "languages",
        "createSql": "CREATE TABLE IF NOT EXISTS `${TABLE_NAME}` (`langauge` TEXT NOT NULL, `value` TEXT NOT NULL, PRIMARY KEY(`langauge`))",
        "fields": [
          {
            "fieldPath": "langauge",
            "columnName": "langauge",
            "affinity": "TEXT",
            "notNull": true
          },
          {
            "fieldPath": "value",
            "columnName": "value",
            "affinity": "TEXT",
            "notNull": true
          }
        ],
        "primaryKey": {
          "columnNames": [
            "langauge"
          ],
          "autoGenerate": false
        },
        "indices": [],
        "foreignKeys": []
      },
      {
        "tableName": "words",
        "createSql": "CREATE TABLE IF NOT EXISTS `${TABLE_NAME}` (`id` INTEGER PRIMARY KEY AUTOINCREMENT NOT NULL, `orginal` TEXT NOT NULL, `translation` TEXT NOT NULL, `failed` INTEGER NOT NULL)",
        "fields": [
          {
            "fieldPath": "id",
            "columnName": "id",
            "affinity": "INTEGER",
            "notNull": true
          },
          {
            "fieldPath": "orginal",
            "columnName": "orginal",
            "affinity": "TEXT",
            "notNull": true
          },
          {
            "fieldPath": "translation",
            "columnName": "translation",
            "affinity": "TEXT",
            "notNull": true
          },
          {
            "fieldPath": "failed",
            "columnName": "failed",
            "affinity": "INTEGER",
            "notNull": true
          }
        ],
        "primaryKey": {
          "columnNames": [
            "id"
          ],
          "autoGenerate": true
        },
        "indices": [],
        "foreignKeys": []
      }
    ],
    "views": [],
    "setupQueries": [
      "CREATE TABLE IF NOT EXISTS room_master_table (id INTEGER PRIMARY KEY,identity_hash TEXT)",
      "INSERT OR REPLACE INTO room_master_table (id,identity_hash) VALUES(42, 'a6b32dc52c7ca2c525693b6792d3da45')"
    ]
  }
}